elo_calculator-0.1.1.dist-info/METADATA
elo_calculator-0.1.1.dist-info/WHEEL
elo_calculator/__init__.py
elo_calculator/elo_calculator.cpython-311-aarch64-linux-gnu.so
elo_calculator-0.1.1.dist-info/RECORD
