Metadata-Version: 2.4
Name: elo_calculator
Version: 0.1.1
Classifier: Programming Language :: Rust
Classifier: Programming Language :: Python :: Implementation :: CPython
Classifier: Programming Language :: Python :: Implementation :: PyPy
Summary: An elo calculator built in Rust. Capable of calculating elos for 1v1 and multiplayer events.
Requires-Python: >=3.8
